resultsdbpy/__init__.py
resultsdbpy/controller/__init__.py
resultsdbpy/controller/api_routes.py
resultsdbpy/controller/archive_controller.py
resultsdbpy/controller/archive_controller_unittest.py
resultsdbpy/controller/bug_tracker_controller.py
resultsdbpy/controller/ci_controller.py
resultsdbpy/controller/ci_controller_unittest.py
resultsdbpy/controller/commit_controller.py
resultsdbpy/controller/commit_controller_unittest.py
resultsdbpy/controller/configuration.py
resultsdbpy/controller/configuration_controller.py
resultsdbpy/controller/configuration_controller_unittest.py
resultsdbpy/controller/configuration_unittest.py
resultsdbpy/controller/failure_controller.py
resultsdbpy/controller/failure_controller_unittest.py
resultsdbpy/controller/suite_controller.py
resultsdbpy/controller/suite_controller_unittest.py
resultsdbpy/controller/test_controller.py
resultsdbpy/controller/test_controller_unittest.py
resultsdbpy/controller/upload_controller.py
resultsdbpy/controller/upload_controller_unittest.py
resultsdbpy/example/__init__.py
resultsdbpy/example/environment.py
resultsdbpy/example/main.py
resultsdbpy/example/worker.py
resultsdbpy/flask_support/__init__.py
resultsdbpy/flask_support/flask_test_context.py
resultsdbpy/flask_support/flask_testcase.py
resultsdbpy/model/__init__.py
resultsdbpy/model/archive_context.py
resultsdbpy/model/archive_context_unittest.py
resultsdbpy/model/archiver.py
resultsdbpy/model/cassandra_archiver.py
resultsdbpy/model/cassandra_context.py
resultsdbpy/model/cassandra_context_unittest.py
resultsdbpy/model/casserole.py
resultsdbpy/model/casserole_unittest.py
resultsdbpy/model/ci_context.py
resultsdbpy/model/ci_context_unittest.py
resultsdbpy/model/commit_context.py
resultsdbpy/model/commit_context_unittest.py
resultsdbpy/model/configuration_context.py
resultsdbpy/model/configuration_context_unittest.py
resultsdbpy/model/docker.py
resultsdbpy/model/docker_unittest.py
resultsdbpy/model/failure_context.py
resultsdbpy-3.1.9.dist-info/LICENSE
resultsdbpy-3.1.9.dist-info/METADATA
resultsdbpy-3.1.9.dist-info/WHEEL
resultsdbpy-3.1.9.dist-info/top_level.txt
resultsdbpy-3.1.9.dist-info/RECORD
