Metadata-Version: 2.1
Name: resultsdbpy
Version: 3.1.9
Summary: Library for visualizing, processing and storing test results.
Home-page: https://github.com/WebKit/WebKit/tree/main/Tools/Scripts/libraries/resultsdbpy
Author: Jonathan Bedard
Author-email: jbedard@apple.com
License: Modified BSD
Keywords: database history results testing webkit
Classifier: Development Status :: 4 - Beta
Classifier: Framework :: Flask
Classifier: Intended Audience :: Developers
Classifier: License :: OSI Approved :: BSD License
Classifier: Operating System :: MacOS
Classifier: Natural Language :: English
Classifier: Programming Language :: Python :: 3 :: Only
Classifier: Topic :: Software Development :: Libraries :: Python Modules
Classifier: Topic :: Software Development :: Testing
License-File: LICENSE
Requires-Dist: boto3
Requires-Dist: cassandra-driver
Requires-Dist: fakeredis
Requires-Dist: lupa
Requires-Dist: pycryptodome
Requires-Dist: redis
Requires-Dist: xmltodict
Requires-Dist: selenium
Requires-Dist: webkitcorepy
Requires-Dist: webkitscmpy
Requires-Dist: webkitflaskpy
